qixin_add_mcp_demo/__init__.py
qixin_add_mcp_demo/server.py
qixin_add_mcp_demo-0.1.0.dist-info/WHEEL
qixin_add_mcp_demo-0.1.0.dist-info/entry_points.txt
qixin_add_mcp_demo-0.1.0.dist-info/METADATA
qixin_add_mcp_demo-0.1.0.dist-info/RECORD
