Metadata-Version: 2.3
Name: qixin-add-mcp-demo
Version: 0.1.0
Summary: Add your description here
Author: qixin1106
Author-email: qixin1106 <63401364@qq.com>
Requires-Dist: mcp[cli]>=1.25.0
Requires-Python: >=3.10
